{
    "Description" : {
        "Id" : "022M",
        "Name" : "022M",
        "Details" : "Random",
        "Icon" : "022M"
    },
    "ID" : "022M",
    "backgroundColor" : {
        "r" : 0,
        "g" : 0,
        "b" : 0,
        "a" : 0
    },
    "headMesh" : 0.5,
    "hairMesh" : 15,
    "beardMesh" : 0,
    "suitMesh" : 1,
    "scar" : 11,
    "lightRig" : 5,
    "cameraPosition" : 1,
    "complexionTex" : 4,
    "eyebrowTex" : 4,
    "tattooTex" : 7,
    "actualTattooTex" : 0,
    "weights" : [
        35.10583,
        0.2305309,
        32.00737,
        14.88343,
        11.74547,
        6.027355
    ],
    "browOffsetY" : 0.003261306,
    "browOffsetZ" : 7.839883E-05,
    "noseBridgeScale" : -0.1027247,
    "noseTipScale" : -0.1252211,
    "chinScale" : -0.07074463,
    "cheekOffsetY" : 0.002219252,
    "eyeWidth" : -0.03508067,
    "jawWidth" : 0.01351,
    "animation" : 2,
    "isCommander" : true,
    "skinToneId" : "Skin_04",
    "eyeColorId" : "Eye_02",
    "hairRootId" : "Hair_12",
    "hairTipId" : "Hair_12",
    "tattooColorId" : "Tattoo_06",
    "lipColorId" : "Lip_01",
    "customPortraitSaveVersion" : 0
}
