{
    "Description" : {
        "Id" : "Male_Rank3_2",
        "Name" : "Male_Rank3_2",
        "Details" : "Random",
        "Icon" : "Male_Rank3_2"
    },
    "ID" : "Male_Rank3_2",
    "backgroundColor" : {
        "r" : 0,
        "g" : 0,
        "b" : 0,
        "a" : 0
    },
    "headMesh" : 0.5,
    "hairMesh" : 8,
    "beardMesh" : 0,
    "suitMesh" : 2,
    "scar" : 7,
    "lightRig" : 4,
    "cameraPosition" : 1,
    "complexionTex" : 3,
    "eyebrowTex" : 2,
    "tattooTex" : 3,
    "actualTattooTex" : 5,
    "weights" : [
        31.70093,
        0.7019297,
        25.68223,
        31.47356,
        9.873083,
        0.5682674
    ],
    "browOffsetY" : 0.002012586,
    "browOffsetZ" : 0.001802099,
    "noseBridgeScale" : 0.1533879,
    "noseTipScale" : 0.2844712,
    "chinScale" : 0.07639031,
    "cheekOffsetY" : 0.003088858,
    "eyeWidth" : 0.03555659,
    "jawWidth" : 0.09213698,
    "animation" : 1,
    "isCommander" : true,
    "skinToneId" : "Skin_04",
    "eyeColorId" : "Eye_07",
    "hairRootId" : "Hair_09",
    "hairTipId" : "Hair_09",
    "tattooColorId" : "Tattoo_03",
    "lipColorId" : "Lip_01",
    "customPortraitSaveVersion" : 0
}
