{
    "Description" : {
        "Id" : "replacement_dekker",
        "Name" : "replacement_dekker",
        "Details" : "Random",
        "Icon" : "replacement_dekker"
    },
    "ID" : "replacement_dekker",
    "backgroundColor" : {
        "r" : 0,
        "g" : 0,
        "b" : 0,
        "a" : 0
    },
    "headMesh" : 0.5,
    "hairMesh" : 12,
    "beardMesh" : 0,
    "suitMesh" : 0,
    "scar" : 5,
    "lightRig" : 1,
    "cameraPosition" : 2,
    "complexionTex" : 2,
    "eyebrowTex" : 5,
    "tattooTex" : 0,
    "actualTattooTex" : 0,
    "weights" : [
        65.0146,
        6.460183,
        1.850891,
        2.111286,
        0.9384462,
        23.62459
    ],
    "browOffsetY" : -0.001706208,
    "browOffsetZ" : 0.001598602,
    "noseBridgeScale" : -0.1219,
    "noseTipScale" : -0.2278286,
    "chinScale" : 0.06077508,
    "cheekOffsetY" : 0.003822486,
    "eyeWidth" : 0.02330959,
    "jawWidth" : -0.06995406,
    "animation" : 1,
    "isCommander" : true,
    "skinToneId" : "Skin_06",
    "eyeColorId" : "Eye_05",
    "hairRootId" : "Hair_04",
    "hairTipId" : "Hair_04",
    "tattooColorId" : "Tattoo_10",
    "lipColorId" : "Lip_01",
    "customPortraitSaveVersion" : 0
}
