{
    "Description" : {
        "Id" : "1a",
        "Name" : "1a",
        "Details" : "Random",
        "Icon" : "1a"
    },
    "ID" : "1a",
    "backgroundColor" : {
        "r" : 0,
        "g" : 0,
        "b" : 0,
        "a" : 0
    },
    "headMesh" : 0.5,
    "hairMesh" : 4,
    "beardMesh" : 0,
    "suitMesh" : 0,
    "scar" : 0,
    "lightRig" : 1,
    "cameraPosition" : 1,
    "complexionTex" : 1,
    "eyebrowTex" : 2,
    "tattooTex" : 1,
    "actualTattooTex" : 14,
    "weights" : [
        14.76583,
        3.012322,
        8.647389,
        21.56166,
        28.00089,
        24.01191
    ],
    "browOffsetY" : -0.00469195,
    "browOffsetZ" : -0.005266916,
    "noseBridgeScale" : 0.1259327,
    "noseTipScale" : -0.04230835,
    "chinScale" : 0.0153651,
    "cheekOffsetY" : -0.003269889,
    "eyeWidth" : -0.006046718,
    "jawWidth" : 0.04918336,
    "animation" : 4,
    "isCommander" : true,
    "skinToneId" : "Skin_03",
    "eyeColorId" : "Eye_07",
    "hairRootId" : "Hair_00",
    "hairTipId" : "Hair_00",
    "tattooColorId" : "Tattoo_10",
    "lipColorId" : "Lip_01",
    "customPortraitSaveVersion" : 0
}
